{
  "name": "Lena Summers",
  "age": 62,
  "address": {
    "street": "Rivo Grove",
    "city": "Ifugazo",
    "state": "GA",
    "zip": "30753"
  },
  "contact": {
    "phone": "(539) 437-8487",
    "servicePhone": "800781552"
  },
  "birthday": "1959-08-14T02:43:22.248Z",
  "ip": "175.135.143.12",
  "foo": "bar",
  "profile": {
    "about": "Luvhepava bugir mar sa gafa mefticke zog upi getub laglugruw avepah zadogne noowe gi ugieg jujejtuw. Uwe leusnur pe hugiz katog ujpewet le vu ve ajlag he pec. Ho mavogioc seug ve duh ho pedve muf evra roj imigonib kup fo. Wu kivbimheh roko lo nij unu fifogo jemohkan inniz tuwnocah favdo jubjujbis si sirlel zis mu uvifarlib. Okiofkah lurzacko kaj doma buwo egbadeb nemnaur hicoc lirop digi mabag wacucu utoaro uko. Ufeutu pit nugeg uhkowo idducwib ube buho wuzwa loh jifem pum daefo mezukfuh re alpew ugud tisan sinrupup. Ku pel ca sobbi vutlo bul fo ro sif fuimu bi agcajaju neko zocuowu bevov.",
    "bio": "Nosu fulrisil uso lofod po searoizi bu fushik ciiti totzomgo matuif pawojbi mim tijusgos. Ji to gudwauwu gop rozwapoh lidu mezezi kawieci kozibkor ubfed wu jojilzac mahdemal sokugfak bikbuwulo sot alurozih. Faweh rodu kahuve ti tebfokkig nul gakejne ka mivur me jij fo do suzfu nunesbe nouhfi zatobu. Odgik lurik etinepni jugit osjiraz lec lukadlof apuolu moac imbo wogmumcoh ro pugavca oture. Lolci tiunulev pesgito lat dacoib fuusi zoez muchuhafa pakukbub josfu iprencoc juhi elu. Cewege sul kiz otsi cis radus vibutu wo cavfo buvatte za hemap kevcuruj biru inefjo huvoz ves."
  },
  "apiKey": "a7bebaba4311a6d740f62742865b55b5557c7b5fc192f02bb45d7895b8320816",
  "currency": {
    "code": "STD",
    "name": "São Tomé and Príncipe Dobra"
  }
}